{
    "Ar36": {
        "error": 0.0002497043679158075, 
        "filter_outliers_dict": {
            "filter_outliers": true, 
            "iterations": 2, 
            "std_devs": 2
        }, 
        "fit": "Parabolic", 
        "value": 0.005822779632077493
    }, 
    "Ar37": {
        "error": 0.011028351732986628, 
        "filter_outliers_dict": {
            "filter_outliers": true, 
            "iterations": 2, 
            "std_devs": 2
        }, 
        "fit": "linear", 
        "value": -0.2838606756722912
    }, 
    "Ar38": {
        "error": 0.01255680856417925, 
        "filter_outliers_dict": {
            "filter_outliers": true, 
            "iterations": 2, 
            "std_devs": 2
        }, 
        "fit": "linear", 
        "value": -0.12321527881594693
    }, 
    "Ar39": {
        "error": 0.025960752168921245, 
        "filter_outliers_dict": {
            "filter_outliers": true, 
            "iterations": 2, 
            "std_devs": 2
        }, 
        "fit": "Parabolic", 
        "value": -0.005834234647552926
    }, 
    "Ar40": {
        "error": 0.02155366362879181, 
        "filter_outliers_dict": {
            "filter_outliers": true, 
            "iterations": 2, 
            "std_devs": 2
        }, 
        "fit": "Parabolic", 
        "value": -0.33280210317692027
    }
}