{
    "AX": {
        "error": 0.010729967085375448,
        "filter_outliers_dict": {
            "filter_outliers": true,
            "iterations": 1,
            "std_devs": 2,
            "use_iqr_filtering": false,
            "use_standard_deviation_filtering": false
        },
        "fit": "Average",
        "fn": 116,
        "include_baseline_error": false,
        "n": 120,
        "outlier_excluded": [
            56,
            104,
            108,
            22
        ],
        "reviewed": true,
        "user_excluded": [],
        "value": -0.040499759267951393
    },
    "CDD": {},
    "H1": {
        "error": 0.010870248396501473,
        "filter_outliers_dict": {
            "filter_outliers": true,
            "iterations": 1,
            "std_devs": 2,
            "use_iqr_filtering": false,
            "use_standard_deviation_filtering": false
        },
        "fit": "Average",
        "fn": 115,
        "include_baseline_error": false,
        "n": 120,
        "outlier_excluded": [
            48,
            2,
            107,
            117,
            102
        ],
        "reviewed": true,
        "user_excluded": [],
        "value": -0.03752014561778987
    },
    "H2": {
        "error": 0.00950901723523051,
        "filter_outliers_dict": {
            "filter_outliers": true,
            "iterations": 1,
            "std_devs": 2
        },
        "fit": "average",
        "value": 0.02540167236373981
    },
    "L1": {
        "error": 0.009359763025663853,
        "filter_outliers_dict": {
            "filter_outliers": true,
            "iterations": 1,
            "std_devs": 2,
            "use_iqr_filtering": false,
            "use_standard_deviation_filtering": false
        },
        "fit": "Average",
        "fn": 114,
        "include_baseline_error": false,
        "n": 120,
        "outlier_excluded": [
            38,
            13,
            19,
            85,
            25,
            60
        ],
        "reviewed": true,
        "user_excluded": [],
        "value": -0.29715315873424214
    },
    "L2": {},
    "L2(CDD)": {
        "error": 0.0,
        "filter_outliers_dict": {
            "filter_outliers": true,
            "iterations": 1,
            "std_devs": 2
        },
        "fit": "average",
        "value": 0.0
    }
}