{
    "Ar36": {
        "error": 0.004169248745835367, 
        "filter_outliers_dict": {
            "filter_outliers": true, 
            "iterations": 2, 
            "std_devs": 2
        }, 
        "fit": "Parabolic", 
        "value": 3.2268324561832067
    }, 
    "Ar37": {
        "error": 0.011944338326374867, 
        "filter_outliers_dict": {
            "filter_outliers": true, 
            "iterations": 2, 
            "std_devs": 2
        }, 
        "fit": "linear", 
        "value": -0.4204978479926008
    }, 
    "Ar38": {
        "error": 0.012815796920312404, 
        "filter_outliers_dict": {
            "filter_outliers": true, 
            "iterations": 2, 
            "std_devs": 2
        }, 
        "fit": "linear", 
        "value": -1.8611381282958024
    }, 
    "Ar39": {
        "error": 0.024221512523671364, 
        "filter_outliers_dict": {
            "filter_outliers": true, 
            "iterations": 2, 
            "std_devs": 2
        }, 
        "fit": "Parabolic", 
        "value": -1.105123802618169
    }, 
    "Ar40": {
        "error": 0.06186832431499407, 
        "filter_outliers_dict": {
            "filter_outliers": true, 
            "iterations": 2, 
            "std_devs": 2
        }, 
        "fit": "Parabolic", 
        "value": 942.6218569588511
    }
}